phdbot/__init__.py
phdbot/__main__.py
phdbot/example.py
phdbot-0.1.0.dist-info/entry_points.txt
phdbot-0.1.0.dist-info/LICENSE
phdbot-0.1.0.dist-info/WHEEL
phdbot-0.1.0.dist-info/METADATA
phdbot-0.1.0.dist-info/RECORD
