Metadata-Version: 2.1
Name: phdbot
Version: 0.1.0
Summary: Awesome `phdbot` is a Python cli/package created with https://github.com/TezRomacH/python-package-template
Home-page: https://github.com/phdbot/phdbot
License: BSD-3
Author: phdbot
Author-email: domi@phdbot.cloud
Requires-Python: >=3.8,<4.0
Classifier: Development Status :: 3 - Alpha
Classifier: Intended Audience :: Developers
Classifier: License :: OSI Approved :: BSD License
Classifier: License :: Other/Proprietary License
Classifier: Operating System :: OS Independent
Classifier: Programming Language :: Python :: 3
Classifier: Programming Language :: Python :: 3.10
Classifier: Programming Language :: Python :: 3.8
Classifier: Programming Language :: Python :: 3.9
Classifier: Topic :: Software Development :: Libraries :: Python Modules
Requires-Dist: rich (>=10.14.0,<11.0.0)
Requires-Dist: typer[all] (>=0.4.0,<0.5.0)
Project-URL: Repository, https://github.com/phdbot/phdbot
